auth_cord/__init__.py
auth_cord/authorization.py
auth_cord/client.py
auth_cord/connection.py
auth_cord/guild.py
auth_cord/token.py
auth_cord/user.py
auth_cord-0.1.2.dist-info/LICENSE
auth_cord-0.1.2.dist-info/METADATA
auth_cord-0.1.2.dist-info/WHEEL
auth_cord-0.1.2.dist-info/top_level.txt
auth_cord-0.1.2.dist-info/RECORD
