Metadata-Version: 2.1
Name: auth-cord
Version: 0.1.2
Summary: A basic wrapper discord oauth2
Home-page: https://github.com/cibere/auth_cord.py
Author: cibere
Author-email: cibere.dev@gmail.com
License: MIT
Project-URL: Code, https://github.com/cibere/auth_cord
Project-URL: Issue tracker, https://github.com/cibere/auth_cord/issues
Project-URL: Discord/Support Server, https://discord.gg/2MRrJvP42N
Requires-Python: >=3.8
License-File: LICENSE
Requires-Dist: aiohttp
Requires-Dist: typing-extensions
